magneticfielddb.py
magneticfielddb-data/circular.json
magneticfielddb-data/enrx_tcv.json
magneticfielddb-data/enrx_torpex.json
magneticfielddb-data/guenter.json
magneticfielddb-data/toroidal.json
magneticfielddb-data/AUG/Iconst_Te_70eV_B0_2T.json
magneticfielddb-data/AUG/falchetto_Iconst_Te_150eV_B0_2T.json
magneticfielddb-data/COMPASS/Iconst.json
magneticfielddb-data/COMPASS/Iconst_woX.json
magneticfielddb-data/COMPASS/Iconst_woX_circ.json
magneticfielddb-data/COMPASS/compass_-1X.json
magneticfielddb-data/COMPASS/compass_-2X.json
magneticfielddb-data/COMPASS/compass_1X.json
magneticfielddb-data/COMPASS/compass_2X.json
magneticfielddb-data/COMPASS/woX_Taylor.json
magneticfielddb-data/COMPASS/woX_circ_Taylor.json
magneticfielddb-data/TJ-K/Iconst.json
magneticfielddb-data/TJ-K/Iconst_elong.json
magneticfielddb-data/TJ-K/Iconst_elong_d_e_AUG.json
magneticfielddb-data/TJ-K/Taylor.json
magneticfielddb-data/TJ-K/Taylor_circ.json
magneticfielddb-data/TJ-K/Taylor_elong.json
magneticfielddb-data/TJ-K/rfp_elong.json
magneticfielddb-data/TJ-K/woX_rfp_elong.json
magneticfielddb-0.1.1.dist-info/METADATA
magneticfielddb-0.1.1.dist-info/WHEEL
magneticfielddb-0.1.1.dist-info/licenses/LICENSE
magneticfielddb-0.1.1.dist-info/RECORD
