Metadata-Version: 2.4
Name: magneticfielddb
Version: 0.1.1
Summary: Store and access magnetic field coefficients for Feltor
Project-URL: Source, https://github.com/mwiesenberger/magneticfielddb
Project-URL: Tracker, https://github.com/mwiesenberger/magneticfielddb/issues
Author-email: Matthias Wiesenberger <mattwi@fysik.dtu.dk>
License: MIT License
License-File: LICENSE
Classifier: License :: OSI Approved :: MIT License
Classifier: Operating System :: OS Independent
Classifier: Programming Language :: Python :: 3
Classifier: Topic :: Scientific/Engineering
Classifier: Topic :: Software Development :: Libraries
Classifier: Topic :: Utilities
Requires-Python: >=3.10
Requires-Dist: importlib-resources>=6.5.2
Provides-Extra: jupyter
Requires-Dist: jupyterlab>=4.3.5; extra == 'jupyter'
Requires-Dist: matplotlib>=3.10.1; extra == 'jupyter'
Requires-Dist: netcdf4>=1.7.2; extra == 'jupyter'
Requires-Dist: numpy>=2.2.3; extra == 'jupyter'
Requires-Dist: scipy>=1.15.2; extra == 'jupyter'
Requires-Dist: simplesimdb>=1.1.1; extra == 'jupyter'
Provides-Extra: lint
Requires-Dist: ruff; extra == 'lint'
Provides-Extra: test
Requires-Dist: pytest; extra == 'test'
